whiffle_client/__init__.py
whiffle_client/auth.py
whiffle_client/base_client.py
whiffle_client/client.py
whiffle_client/decorators.py
whiffle_client/entrypoints.py
whiffle_client/io.py
whiffle_client/analysis/__init__.py
whiffle_client/analysis/io.py
whiffle_client/analysis/plot.py
whiffle_client/analysis/scatter.py
whiffle_client/analysis/skill.py
whiffle_client/analysis/utils.py
whiffle_client/common/components/base.py
whiffle_client/common/mapping/base.py
whiffle_client/forecast/__init__.py
whiffle_client/forecast/client.py
whiffle_client/forecast/components/__init__.py
whiffle_client/forecast/components/asset_model.py
whiffle_client/forecast/components/forecast_model.py
whiffle_client/forecast/components/observation_model.py
whiffle_client/forecast/mapping/__init__.py
whiffle_client/forecast/mapping/asset_model.py
whiffle_client/forecast/mapping/forecast_model.py
whiffle_client/forecast/mapping/observation_model.py
whiffle_client/loaders/__init__.py
whiffle_client/loaders/csv.py
whiffle_client/resources/example_generic_params.json
whiffle_client/resources/example_yaml_include.yaml
whiffle_client/resources/example_yaml_include_metmasts.yaml
whiffle_client/resources/whiffle_config.yaml
whiffle_client/snippets/create_mock_powercurve.py
whiffle_client/wind/__init__.py
whiffle_client/wind/client.py
whiffle_client/wind/components/__init__.py
whiffle_client/wind/components/dates.py
whiffle_client/wind/components/domain.py
whiffle_client/wind/components/geometries.py
whiffle_client/wind/components/metmast.py
whiffle_client/wind/components/turbine.py
whiffle_client/wind/components/turbine_model_specs.py
whiffle_client/wind/components/wind_simulation_task.py
whiffle_client/wind/components/windfarm.py
whiffle_client/wind/mapping/atlas.py
whiffle_client/wind/mapping/turbine_model_specs.py
whiffle_client/wind/mapping/wind_simulation_tasks.py
whiffle_client-0.5.2.dist-info/licenses/LICENCE.txt
whiffle_client-0.5.2.dist-info/METADATA
whiffle_client-0.5.2.dist-info/WHEEL
whiffle_client-0.5.2.dist-info/entry_points.txt
whiffle_client-0.5.2.dist-info/top_level.txt
whiffle_client-0.5.2.dist-info/RECORD
