Metadata-Version: 2.4
Name: whiffle_client
Version: 0.5.2
Summary: Python based web client to interact with Whiffle services
Classifier: Programming Language :: Python :: 3
Classifier: License :: OSI Approved :: MIT License
Classifier: Operating System :: OS Independent
Requires-Python: >=3.9
License-File: LICENCE.txt
Requires-Dist: click~=8.0.4
Requires-Dist: PyYAML~=6.0
Requires-Dist: pyyaml-include~=2.1
Requires-Dist: platformdirs~=4.0.0
Requires-Dist: requests
Provides-Extra: analysis
Requires-Dist: pandas~=2.2.0; extra == "analysis"
Requires-Dist: numpy; extra == "analysis"
Requires-Dist: scipy; extra == "analysis"
Requires-Dist: scikit-learn; extra == "analysis"
Requires-Dist: xarray>=2022.12.0; extra == "analysis"
Requires-Dist: netcdf4; extra == "analysis"
Requires-Dist: matplotlib; extra == "analysis"
Requires-Dist: seaborn; extra == "analysis"
Requires-Dist: hvplot; extra == "analysis"
Requires-Dist: jupyter; extra == "analysis"
Requires-Dist: jupyter_bokeh; extra == "analysis"
Dynamic: license-file
